anyioc/__init__.py
anyioc/_servicesmap.py
anyioc/_utils.py
anyioc/builder.py
anyioc/err.py
anyioc/g.py
anyioc/ioc.py
anyioc/ioc_resolver.py
anyioc/ioc_service_info.py
anyioc/symbols.py
anyioc/utils.py
anyioc/utils_conf.py
anyioc-0.15.0.dist-info/LICENSE
anyioc-0.15.0.dist-info/METADATA
anyioc-0.15.0.dist-info/WHEEL
anyioc-0.15.0.dist-info/RECORD
