Metadata-Version: 2.1
Name: anyioc
Version: 0.15.0
Summary: Another simple ioc framework for python
License: MIT
Author: Cologler
Author-email: skyoflw@gmail.com
Requires-Python: >=3.8,<4.0
Classifier: License :: OSI Approved :: MIT License
Classifier: Programming Language :: Python :: 3
Classifier: Programming Language :: Python :: 3.8
Classifier: Programming Language :: Python :: 3.9
Classifier: Programming Language :: Python :: 3.10
Classifier: Programming Language :: Python :: 3.11
